hwhkit/__init__.py
hwhkit/connection/__init__.py
hwhkit/connection/mqtt/__init__.py
hwhkit/connection/mqtt/async_client.py
hwhkit/connection/mqtt/client.py
hwhkit/connection/mqtt/plugins/__init__.py
hwhkit/connection/mqtt/plugins/encryption.py
hwhkit/connection/mqtt/plugins/proto.py
hwhkit/connection/mqtt/plugins/proto_pb2.py
hwhkit/llm/__init__.py
hwhkit/llm/config/__init__.py
hwhkit/llm/models/__init__.py
hwhkit/llm/models/alibaba.py
hwhkit/llm/models/anthropic.py
hwhkit/llm/models/bedrock.py
hwhkit/llm/models/deepseek.py
hwhkit/llm/models/lingyi.py
hwhkit/llm/models/moonshot.py
hwhkit/llm/models/nvidia.py
hwhkit/llm/models/ollama.py
hwhkit/llm/models/openai.py
hwhkit/llm/models/siliconflow.py
hwhkit/llm/models/zhipu.py
hwhkit/llm/moe/__init__.py
hwhkit/llm/moe/router.py
hwhkit/utils/__init__.py
hwhkit/utils/file/__init__.py
hwhkit/utils/file/handler.py
hwhkit/utils/hash/__init__.py
hwhkit/utils/http/HttpAsyncClient.py
hwhkit/utils/http/HttpResult.py
hwhkit/utils/http/__init__.py
hwhkit/utils/security/__init__.py
hwhkit/utils/security/aes.py
hwhkit/utils/security/ecc.py
hwhkit/utils/security/rsa.py
hwhkit-1.0.21.dist-info/LICENSE
hwhkit-1.0.21.dist-info/METADATA
hwhkit-1.0.21.dist-info/WHEEL
hwhkit-1.0.21.dist-info/top_level.txt
hwhkit-1.0.21.dist-info/RECORD
